classifier/__init__.py
classifier/script_global.py
classifier/sentimentPipeline.py
classifier/data/Cities.txt
classifier/data/Countries.txt
classifier/data/dictConjug.json
classifier/data/expressions.txt
classifier/img/bad_baby.jpg
classifier/img/good_baby.jpg
classifier/model/sentiment_pipeline.pkl
spanish_sentiment_analysis-1.0.0.dist-info/DESCRIPTION.rst
spanish_sentiment_analysis-1.0.0.dist-info/METADATA
spanish_sentiment_analysis-1.0.0.dist-info/RECORD
spanish_sentiment_analysis-1.0.0.dist-info/WHEEL
spanish_sentiment_analysis-1.0.0.dist-info/metadata.json
spanish_sentiment_analysis-1.0.0.dist-info/top_level.txt
