Metadata-Version: 1.1
Name: spanish-sentiment-analysis
Version: 1.0.0
Summary: A sentiment analysis classifier in spanish.
Home-page: UNKNOWN
Author: Elliot Hofman
Author-email: elliot.hofman@gmail.com
License: MIT
Keywords: natural language processing sentiment analysis
Platform: UNKNOWN
Classifier: Development Status :: 4 - Beta
Classifier: Topic :: Software Development :: Build Tools
Classifier: License :: OSI Approved :: MIT License
Classifier: Programming Language :: Python :: 3
Classifier: Programming Language :: Python :: 3.3
Classifier: Programming Language :: Python :: 3.4
Classifier: Programming Language :: Python :: 3.5
